rtl/pisoUnit.v
`timescale 1ns/1ps

module pisoUnit #(parameter WIDTH = 8) (
    input clk,
    input [WIDTH-1:0] data,
    input reset,
    output reg q
);

    reg [WIDTH-1:0] shift_reg;
    // reg [WIDTH-1:0] hold_reg;
    reg [3:0] shift_counter;

    always @ (posedge clk or posedge reset) begin
        if (reset) begin
            shift_reg <= 0;
            // hold_reg <= 0;
            shift_counter <= 0;
            q <= 1'b0;
        end else begin
            shift_counter <= shift_counter + 1;
            if (shift_counter == 0) begin
                shift_reg <= data;
            end else begin
                q <= shift_reg[0];
                shift_reg <= shift_reg >> 1;
            end
        end
    end

endmodule

tb/pisoTest.v
`timescale 1ns/1ps

module pisoTest;

parameter WIDTH = 8;

reg clk;
reg [WIDTH-1:0] data;
reg clear;
wire q;

pisoUnit dut (
    .data(data),
    .reset(clear),
    .clk(clk),
    .q(q)
);

always #5 clk = ~clk; // Toggle clock every 5ns, so clock cycle = 10ns

initial begin
    // Initial setup
    clk = 0;
    clear = 1;
    data = 8'b0;

    $dumpfile("pisoDump.vcd");
    $dumpvars(0, pisoTest);

    $display("Header:");
    $display("time=%0tps | input=%0h | output=%0h", $time, data, q);
    $display("---");
    $display("");

    // Start the simi
    clear = 0;

    // Test case #1
    #5 data = 8'b10011001;

    $display("Data Block #1 -> 10011001");
    $display("---");
    #10;
    repeat (8) begin
        #10;
        $display("time=%0tps | input=%0h | output=%0h", $time, data, q);
    end

    #10 clear = 1;

    // Test case #2
    #5 data = 8'b01100001;

    clear = 0;

    $display("");
    $display("Data Block #2 -> 01100001");
    $display("---");
    #10;
    repeat (8) begin
        #10;
        $display("time=%0tps | input=%0h | output=%0h", $time, data, q);
    end

    clear = 1;

    // Finish sim 50ns later
    #50 $finish;
end

endmodule

sim/waveforms/pisoDump.vcd
$version Generated by VerilatedVcd $end
$timescale 1ps $end
 $scope module TOP $end
  $scope module pisoTest $end
   $var wire 32 ) WIDTH [31:0] $end
   $var wire 1 & clk $end
   $var wire 8 ' data [7:0] $end
   $var wire 1 ( clear $end
   $var wire 1 # q $end
   $scope module dut $end
    $var wire 32 ) WIDTH [31:0] $end
    $var wire 1 & clk $end
    $var wire 8 ' data [7:0] $end
    $var wire 1 ( reset $end
    $var wire 1 # q $end
    $var wire 8 $ shift_reg [7:0] $end
    $var wire 4 % shift_counter [3:0] $end
   $upscope $end
  $upscope $end
 $upscope $end
$enddefinitions $end


#0
0#
b00000000 $
b0000 %
0&
b00000000 '
0(
b00000000000000000000000000001000 )
#5000
b10011001 $
b0001 %
1&
b10011001 '
#10000
0&
#15000
1#
b01001100 $
b0010 %
1&
#20000
0&
#25000
0#
b00100110 $
b0011 %
1&
#30000
0&
#35000
b00010011 $
b0100 %
1&
#40000
0&
#45000
1#
b00001001 $
b0101 %
1&
#50000
0&
#55000
b00000100 $
b0110 %
1&
#60000
0&
#65000
0#
b00000010 $
b0111 %
1&
#70000
0&
#75000
b00000001 $
b1000 %
1&
#80000
0&
#85000
1#
b00000000 $
b1001 %
1&
#90000
0&
#95000
0#
b1010 %
1&
#100000
0&
#105000
b0000 %
1&
1(
#110000
0&
b01100001 '
0(
#115000
b01100001 $
b0001 %
1&
#120000
0&
#125000
1#
b00110000 $
b0010 %
1&
#130000
0&
#135000
0#
b00011000 $
b0011 %
1&
#140000
0&
#145000
b00001100 $
b0100 %
1&
#150000
0&
#155000
b00000110 $
b0101 %
1&
#160000
0&
#165000
b00000011 $
b0110 %
1&
#170000
0&
#175000
1#
b00000001 $
b0111 %
1&
#180000
0&
#185000
b00000000 $
b1000 %
1&
#190000
0&
#195000
0#
b1001 %
1&
#200000
b0000 %
0&
1(
