rtl/baudUnit.v
`timescale 1ns/1ps

module baudUnit (
    input clk,
    input reset,
    output reg baud,
    output reg sample
);

parameter SYSTEM_CLOCK_FREQ = 100000000; // 100 MHz
parameter BAUD_RATE = 115200;

localparam int DIVIDER = SYSTEM_CLOCK_FREQ / BAUD_RATE;

reg [15:0] counter;

always @(posedge clk or posedge reset) begin
    if (reset) begin
        counter <= 0;
        baud <= 0;
        sample <= 0;
    end else if (counter >= DIVIDER - 1) begin
        counter <= 0;
        baud <= ~baud;
        sample <= 0;
    end else if (counter >= DIVIDER / 2) begin
        sample <= 1;
        counter <= counter + 1;
    end else begin
        counter <= counter + 1;
    end
end

endmodule

rtl/dff.v
`timescale 1ns/1ps

module dff (
    input d,
    input clk,
    input reset,
    output reg baud,
    output reg [3:0] baud_counter,
    output reg [3:0] shift_counter,
    output reg sample,
    output reg start,
    output reg q
);

    baudUnit baudGen (
        .clk(clk),
        .reset(reset),
        .baud(baud),
        .sample(sample)
    );

always @ (posedge sample) begin
    if (reset) begin
        q <= 1'b0;
        shift_counter <= 0;
    end else if (start) begin
        q <= d;
        shift_counter <= shift_counter + 1;
    end // else if (shift_counter == 10 && ) begin
    // end
end

always @(posedge baud) begin
    if (reset) begin
        baud_counter <= 0;
        start <= 0;
    end else begin
        baud_counter <= baud_counter + 1;
    end if (baud_counter == 1 - 1 && ~d) begin
        start <= 1;
    end
end
    
endmodule

rtl/sipoUnit.v
`timescale 1ns/1ps

module sipoUnit #(parameter WIDTH = 8) (
    input wire data_in,
    input wire hold_value,
    input wire reset,
    input wire clk,
    // input wire [3:0] bit_count,
    output reg baud,
    output wire sample,
    output reg start,
    output reg [WIDTH-1:0] q
);

    baudUnit dut (
        .clk(clk),
        .reset(reset),
        .baud(baud),
        .sample(sample)
    );

    dff dff0 (
        .d(hold_value ? q[0] : data_in),
        .reset(reset),
        // .shift_counter(bit_count),
        .clk(clk),
        .q(q[0]),
        .sample(sample)
        );

    generate
        for (genvar i = 0; i < WIDTH-1; i++) begin
            dff dff_inst (
                .d(hold_value ? q[i+1] : q[i]),
                .reset(reset),
                // .shift_counter(bit_count),
                .clk(clk),
                .q(q[i+1]),
                .sample(sample)
            );
        end
    endgenerate

    always @(posedge baud or negedge baud) begin
        if (sample) begin
            if (q[0] == 0) begin
               start <= 1;
           end else begin
               start <= 0;
           end
       end
   end

endmodule

rtl/receiver.v
`timescale 1ns/1ps

module receiver (
    input clk,
    input data,
    input reset,
    input hold_value,
    output baud,
    output [7:0] rx,
    output sample,
    // output [3:0] bit_count,
    output start
);

    sipoUnit sipo (
        .data_in(data),
        .hold_value(hold_value),
        .reset(reset),
        // .bit_count(bit_count),
        .baud(baud),
        .clk(clk),
        .q(rx)
    );

    baudUnit baudGen (
        .clk(clk),
        .baud(baud),
        .reset(reset),
        .sample(sample)
    );

endmodule

tb/receiverTest.v
`timescale 1ns/1ps

module receiverTest;

parameter WIDTH = 8;

reg clk;
reg data;
wire sample;
reg baud;
reg reset;
reg start;
reg hold_value;
reg [WIDTH-1:0] rx;

    receiver dut (
        .data(data),
        .start(start),
        .hold_value(hold_value),
        .baud(baud),
        .reset(reset),
        .clk(clk),
        .sample(sample),
        .rx(rx)
    );

    baudUnit baudGen (
        .clk(clk),
        .reset(reset),
        .baud(baud),
        .sample(sample)
    );

    always #5 clk = ~clk;
    always if (reset) begin data = 1'b0; end

    initial begin
        data = 1;
        clk = 0;
        $dumpfile("rxDump.vcd");
        $dumpvars;
        $display("time=%0tps", $time);
        $display("input=%0h", data);
        $display("output=%0h", rx[7], rx[6], rx[5], rx[4], rx[3], rx[2], rx[1], rx[0]);
        $display("---");
        #8675 data = 0;
        $display("time=%0tps", $time);
        $display("input=%0h", data);
        $display("output=%0h", rx[7], rx[6], rx[5], rx[4], rx[3], rx[2], rx[1], rx[0]);
        $display("---");
        #8675 data = 1;
        $display("time=%0tps", $time);
        $display("input=%0h", data);
        $display("output=%0h", rx[7], rx[6], rx[5], rx[4], rx[3], rx[2], rx[1], rx[0]);
        $display("---");
        #8675 data = 0;
        $display("time=%0tps", $time);
        $display("input=%0h", data);
        $display("output=%0h", rx[7], rx[6], rx[5], rx[4], rx[3], rx[2], rx[1], rx[0]);
        $display("---");
        #8675 data = 0;
        $display("time=%0tps", $time);
        $display("input=%0h", data);
        $display("output=%0h", rx[7], rx[6], rx[5], rx[4], rx[3], rx[2], rx[1], rx[0]);
        $display("---");
        #8675 data = 1;
        $display("time=%0tps", $time);
        $display("input=%0h", data);
        $display("output=%0h", rx[7], rx[6], rx[5], rx[4], rx[3], rx[2], rx[1], rx[0]);
        $display("---");
        #8675 data = 1;
        $display("time=%0tps", $time);
        $display("input=%0h", data);
        $display("output=%0h", rx[7], rx[6], rx[5], rx[4], rx[3], rx[2], rx[1], rx[0]);
        $display("---");
        #8675 data = 0;
        $display("time=%0tps", $time);
        $display("input=%0h", data);
        $display("output=%0h", rx[7], rx[6], rx[5], rx[4], rx[3], rx[2], rx[1], rx[0]);
        $display("---");
        #8675 data = 0;
        $display("time=%0tps", $time);
        $display("input=%0h", data);
        $display("output=%0h", rx[7], rx[6], rx[5], rx[4], rx[3], rx[2], rx[1], rx[0]);
        $display("---");
        #8675 data = 1;
        $display("time=%0tps", $time);
        $display("input=%0h", data);
        $display("output=%0h", rx[7], rx[6], rx[5], rx[4], rx[3], rx[2], rx[1], rx[0]);
        $display("---");
        #8675 hold_value = 1;
        $display("time=%0tps", $time);
        $display("input=%0h", data);
        $display("output=%0h", rx[7], rx[6], rx[5], rx[4], rx[3], rx[2], rx[1], rx[0]);
        $display("---");
        #8675;
        $display("time=%0tps", $time);
        $display("input=%0h", data);
        $display("output=%0h", rx[7], rx[6], rx[5], rx[4], rx[3], rx[2], rx[1], rx[0]);
        $display("---");
        reset = 1;
        #8675;
        $display("time=%0tps", $time);
        $display("input=%0h", data);
        $display("output=%0h", rx[7], rx[6], rx[5], rx[4], rx[3], rx[2], rx[1], rx[0]);
        $display("---");
        $finish;
    end
endmodule

sim/waveforms/rxDump.vcd
$version Generated by VerilatedVcd $end
$timescale 1ps $end
 $scope module TOP $end
  $scope module receiverTest $end
   $var wire 32 g WIDTH [31:0] $end
   $var wire 1 O clk $end
   $var wire 1 P data $end
   $var wire 1 * sample $end
   $var wire 1 < baud $end
   $var wire 1 Q reset $end
   $var wire 1 h start $end
   $var wire 1 R hold_value $end
   $var wire 8 S rx [7:0] $end
   $scope module baudGen $end
    $var wire 1 O clk $end
    $var wire 1 Q reset $end
    $var wire 1 < baud $end
    $var wire 1 * sample $end
    $var wire 32 i SYSTEM_CLOCK_FREQ [31:0] $end
    $var wire 32 j BAUD_RATE [31:0] $end
    $var wire 32 k DIVIDER [31:0] $end
    $var wire 16 + counter [15:0] $end
   $upscope $end
   $scope module dut $end
    $var wire 1 O clk $end
    $var wire 1 P data $end
    $var wire 1 Q reset $end
    $var wire 1 R hold_value $end
    $var wire 1 < baud $end
    $var wire 8 S rx [7:0] $end
    $var wire 1 * sample $end
    $var wire 1 h start $end
    $scope module baudGen $end
     $var wire 1 O clk $end
     $var wire 1 Q reset $end
     $var wire 1 < baud $end
     $var wire 1 * sample $end
     $var wire 32 i SYSTEM_CLOCK_FREQ [31:0] $end
     $var wire 32 j BAUD_RATE [31:0] $end
     $var wire 32 k DIVIDER [31:0] $end
     $var wire 16 , counter [15:0] $end
    $upscope $end
    $scope module sipo $end
     $var wire 32 g WIDTH [31:0] $end
     $var wire 1 P data_in $end
     $var wire 1 R hold_value $end
     $var wire 1 Q reset $end
     $var wire 1 O clk $end
     $var wire 1 < baud $end
     $var wire 1 = sample $end
     $var wire 1 T start $end
     $var wire 8 S q [7:0] $end
     $scope module dff0 $end
      $var wire 1 U d $end
      $var wire 1 O clk $end
      $var wire 1 Q reset $end
      $var wire 1 > baud $end
      $var wire 4 V baud_counter [3:0] $end
      $var wire 4 - shift_counter [3:0] $end
      $var wire 1 = sample $end
      $var wire 1 W start $end
      $var wire 1 X q $end
      $scope module baudGen $end
       $var wire 1 O clk $end
       $var wire 1 Q reset $end
       $var wire 1 > baud $end
       $var wire 1 = sample $end
       $var wire 32 i SYSTEM_CLOCK_FREQ [31:0] $end
       $var wire 32 j BAUD_RATE [31:0] $end
       $var wire 32 k DIVIDER [31:0] $end
       $var wire 16 ? counter [15:0] $end
      $upscope $end
     $upscope $end
     $scope module dut $end
      $var wire 1 O clk $end
      $var wire 1 Q reset $end
      $var wire 1 < baud $end
      $var wire 1 = sample $end
      $var wire 32 i SYSTEM_CLOCK_FREQ [31:0] $end
      $var wire 32 j BAUD_RATE [31:0] $end
      $var wire 32 k DIVIDER [31:0] $end
      $var wire 16 @ counter [15:0] $end
     $upscope $end
     $scope module genblk1[0] $end
      $scope module dff_inst $end
       $var wire 1 # d $end
       $var wire 1 O clk $end
       $var wire 1 Q reset $end
       $var wire 1 A baud $end
       $var wire 4 Y baud_counter [3:0] $end
       $var wire 4 . shift_counter [3:0] $end
       $var wire 1 = sample $end
       $var wire 1 Z start $end
       $var wire 1 / q $end
       $scope module baudGen $end
        $var wire 1 O clk $end
        $var wire 1 Q reset $end
        $var wire 1 A baud $end
        $var wire 1 = sample $end
        $var wire 32 i SYSTEM_CLOCK_FREQ [31:0] $end
        $var wire 32 j BAUD_RATE [31:0] $end
        $var wire 32 k DIVIDER [31:0] $end
        $var wire 16 B counter [15:0] $end
       $upscope $end
      $upscope $end
     $upscope $end
     $scope module genblk1[1] $end
      $scope module dff_inst $end
       $var wire 1 $ d $end
       $var wire 1 O clk $end
       $var wire 1 Q reset $end
       $var wire 1 C baud $end
       $var wire 4 [ baud_counter [3:0] $end
       $var wire 4 0 shift_counter [3:0] $end
       $var wire 1 = sample $end
       $var wire 1 \ start $end
       $var wire 1 1 q $end
       $scope module baudGen $end
        $var wire 1 O clk $end
        $var wire 1 Q reset $end
        $var wire 1 C baud $end
        $var wire 1 = sample $end
        $var wire 32 i SYSTEM_CLOCK_FREQ [31:0] $end
        $var wire 32 j BAUD_RATE [31:0] $end
        $var wire 32 k DIVIDER [31:0] $end
        $var wire 16 D counter [15:0] $end
       $upscope $end
      $upscope $end
     $upscope $end
     $scope module genblk1[2] $end
      $scope module dff_inst $end
       $var wire 1 % d $end
       $var wire 1 O clk $end
       $var wire 1 Q reset $end
       $var wire 1 E baud $end
       $var wire 4 ] baud_counter [3:0] $end
       $var wire 4 2 shift_counter [3:0] $end
       $var wire 1 = sample $end
       $var wire 1 ^ start $end
       $var wire 1 3 q $end
       $scope module baudGen $end
        $var wire 1 O clk $end
        $var wire 1 Q reset $end
        $var wire 1 E baud $end
        $var wire 1 = sample $end
        $var wire 32 i SYSTEM_CLOCK_FREQ [31:0] $end
        $var wire 32 j BAUD_RATE [31:0] $end
        $var wire 32 k DIVIDER [31:0] $end
        $var wire 16 F counter [15:0] $end
       $upscope $end
      $upscope $end
     $upscope $end
     $scope module genblk1[3] $end
      $scope module dff_inst $end
       $var wire 1 & d $end
       $var wire 1 O clk $end
       $var wire 1 Q reset $end
       $var wire 1 G baud $end
       $var wire 4 _ baud_counter [3:0] $end
       $var wire 4 4 shift_counter [3:0] $end
       $var wire 1 = sample $end
       $var wire 1 ` start $end
       $var wire 1 5 q $end
       $scope module baudGen $end
        $var wire 1 O clk $end
        $var wire 1 Q reset $end
        $var wire 1 G baud $end
        $var wire 1 = sample $end
        $var wire 32 i SYSTEM_CLOCK_FREQ [31:0] $end
        $var wire 32 j BAUD_RATE [31:0] $end
        $var wire 32 k DIVIDER [31:0] $end
        $var wire 16 H counter [15:0] $end
       $upscope $end
      $upscope $end
     $upscope $end
     $scope module genblk1[4] $end
      $scope module dff_inst $end
       $var wire 1 ' d $end
       $var wire 1 O clk $end
       $var wire 1 Q reset $end
       $var wire 1 I baud $end
       $var wire 4 a baud_counter [3:0] $end
       $var wire 4 6 shift_counter [3:0] $end
       $var wire 1 = sample $end
       $var wire 1 b start $end
       $var wire 1 7 q $end
       $scope module baudGen $end
        $var wire 1 O clk $end
        $var wire 1 Q reset $end
        $var wire 1 I baud $end
        $var wire 1 = sample $end
        $var wire 32 i SYSTEM_CLOCK_FREQ [31:0] $end
        $var wire 32 j BAUD_RATE [31:0] $end
        $var wire 32 k DIVIDER [31:0] $end
        $var wire 16 J counter [15:0] $end
       $upscope $end
      $upscope $end
     $upscope $end
     $scope module genblk1[5] $end
      $scope module dff_inst $end
       $var wire 1 ( d $end
       $var wire 1 O clk $end
       $var wire 1 Q reset $end
       $var wire 1 K baud $end
       $var wire 4 c baud_counter [3:0] $end
       $var wire 4 8 shift_counter [3:0] $end
       $var wire 1 = sample $end
       $var wire 1 d start $end
       $var wire 1 9 q $end
       $scope module baudGen $end
        $var wire 1 O clk $end
        $var wire 1 Q reset $end
        $var wire 1 K baud $end
        $var wire 1 = sample $end
        $var wire 32 i SYSTEM_CLOCK_FREQ [31:0] $end
        $var wire 32 j BAUD_RATE [31:0] $end
        $var wire 32 k DIVIDER [31:0] $end
        $var wire 16 L counter [15:0] $end
       $upscope $end
      $upscope $end
     $upscope $end
     $scope module genblk1[6] $end
      $scope module dff_inst $end
       $var wire 1 ) d $end
       $var wire 1 O clk $end
       $var wire 1 Q reset $end
       $var wire 1 M baud $end
       $var wire 4 e baud_counter [3:0] $end
       $var wire 4 : shift_counter [3:0] $end
       $var wire 1 = sample $end
       $var wire 1 f start $end
       $var wire 1 ; q $end
       $scope module baudGen $end
        $var wire 1 O clk $end
        $var wire 1 Q reset $end
        $var wire 1 M baud $end
        $var wire 1 = sample $end
        $var wire 32 i SYSTEM_CLOCK_FREQ [31:0] $end
        $var wire 32 j BAUD_RATE [31:0] $end
        $var wire 32 k DIVIDER [31:0] $end
        $var wire 16 N counter [15:0] $end
       $upscope $end
      $upscope $end
     $upscope $end
    $upscope $end
   $upscope $end
  $upscope $end
 $upscope $end
$enddefinitions $end


#0
0#
0$
0%
0&
0'
0(
0)
0*
b0000000000000000 +
b0000000000000000 ,
b0000 -
b0000 .
0/
b0000 0
01
b0000 2
03
b0000 4
05
b0000 6
07
b0000 8
09
b0000 :
0;
0<
0=
0>
b0000000000000000 ?
b0000000000000000 @
0A
b0000000000000000 B
0C
b0000000000000000 D
0E
b0000000000000000 F
0G
b0000000000000000 H
0I
b0000000000000000 J
0K
b0000000000000000 L
0M
b0000000000000000 N
0O
1P
0Q
0R
b00000000 S
0T
1U
b0000 V
0W
0X
b0000 Y
0Z
b0000 [
0\
b0000 ]
0^
b0000 _
0`
b0000 a
0b
b0000 c
0d
b0000 e
0f
b00000000000000000000000000001000 g
0h
b00000101111101011110000100000000 i
b00000000000000011100001000000000 j
b00000000000000000000001101100100 k
#5000
b0000000000000001 +
b0000000000000001 ,
b0000000000000001 ?
b0000000000000001 @
b0000000000000001 B
b0000000000000001 D
b0000000000000001 F
b0000000000000001 H
b0000000000000001 J
b0000000000000001 L
b0000000000000001 N
1O
#10000
0O
#15000
b0000000000000010 +
b0000000000000010 ,
b0000000000000010 ?
b0000000000000010 @
b0000000000000010 B
b0000000000000010 D
b0000000000000010 F
b0000000000000010 H
b0000000000000010 J
b0000000000000010 L
b0000000000000010 N
1O
#20000
0O
#25000
b0000000000000011 +
b0000000000000011 ,
b0000000000000011 ?
b0000000000000011 @
b0000000000000011 B
b0000000000000011 D
b0000000000000011 F
b0000000000000011 H
b0000000000000011 J
b0000000000000011 L
b0000000000000011 N
1O
#30000
0O
#35000
b0000000000000100 +
b0000000000000100 ,
b0000000000000100 ?
b0000000000000100 @
b0000000000000100 B
b0000000000000100 D
b0000000000000100 F
b0000000000000100 H
b0000000000000100 J
b0000000000000100 L
b0000000000000100 N
1O
#40000
0O
#45000
b0000000000000101 +
b0000000000000101 ,
b0000000000000101 ?
b0000000000000101 @
b0000000000000101 B
b0000000000000101 D
b0000000000000101 F
b0000000000000101 H
b0000000000000101 J
b0000000000000101 L
b0000000000000101 N
1O
#50000
0O
#55000
b0000000000000110 +
b0000000000000110 ,
b0000000000000110 ?
b0000000000000110 @
b0000000000000110 B
b0000000000000110 D
b0000000000000110 F
b0000000000000110 H
b0000000000000110 J
b0000000000000110 L
b0000000000000110 N
1O
#60000
0O
#65000
b0000000000000111 +
b0000000000000111 ,
b0000000000000111 ?
b0000000000000111 @
b0000000000000111 B
b0000000000000111 D
b0000000000000111 F
b0000000000000111 H
b0000000000000111 J
b0000000000000111 L
b0000000000000111 N
1O
#70000
0O
#75000
b0000000000001000 +
b0000000000001000 ,
b0000000000001000 ?
b0000000000001000 @
b0000000000001000 B
b0000000000001000 D
b0000000000001000 F
b0000000000001000 H
b0000000000001000 J
b0000000000001000 L
b0000000000001000 N
1O
#80000
0O
#85000
b0000000000001001 +
b0000000000001001 ,
b0000000000001001 ?
b0000000000001001 @
b0000000000001001 B
b0000000000001001 D
b0000000000001001 F
b0000000000001001 H
b0000000000001001 J
b0000000000001001 L
b0000000000001001 N
1O
#90000
0O
#95000
b0000000000001010 +
b0000000000001010 ,
b0000000000001010 ?
b0000000000001010 @
b0000000000001010 B
b0000000000001010 D
b0000000000001010 F
b0000000000001010 H
b0000000000001010 J
b0000000000001010 L
b0000000000001010 N
1O
#100000
0O
#105000
b0000000000001011 +
b0000000000001011 ,
b0000000000001011 ?
b0000000000001011 @
b0000000000001011 B
b0000000000001011 D
b0000000000001011 F
b0000000000001011 H
b0000000000001011 J
b0000000000001011 L
b0000000000001011 N
1O
#110000
0O
#115000
b0000000000001100 +
b0000000000001100 ,
b0000000000001100 ?
b0000000000001100 @
b0000000000001100 B
b0000000000001100 D
b0000000000001100 F
b0000000000001100 H
b0000000000001100 J
b0000000000001100 L
b0000000000001100 N
1O
#120000
0O
#125000
b0000000000001101 +
b0000000000001101 ,
b0000000000001101 ?
b0000000000001101 @
b0000000000001101 B
b0000000000001101 D
b0000000000001101 F
b0000000000001101 H
b0000000000001101 J
b0000000000001101 L
b0000000000001101 N
1O
#130000
0O
#135000
b0000000000001110 +
b0000000000001110 ,
b0000000000001110 ?
b0000000000001110 @
b0000000000001110 B
b0000000000001110 D
b0000000000001110 F
b0000000000001110 H
b0000000000001110 J
b0000000000001110 L
b0000000000001110 N
1O
#140000
0O
#145000
b0000000000001111 +
b0000000000001111 ,
b0000000000001111 ?
b0000000000001111 @
b0000000000001111 B
b0000000000001111 D
b0000000000001111 F
b0000000000001111 H
b0000000000001111 J
b0000000000001111 L
b0000000000001111 N
1O
#150000
0O
#155000
b0000000000010000 +
b0000000000010000 ,
b0000000000010000 ?
b0000000000010000 @
b0000000000010000 B
b0000000000010000 D
b0000000000010000 F
b0000000000010000 H
b0000000000010000 J
b0000000000010000 L
b0000000000010000 N
1O
#160000
0O
#165000
b0000000000010001 +
b0000000000010001 ,
b0000000000010001 ?
b0000000000010001 @
b0000000000010001 B
b0000000000010001 D
b0000000000010001 F
b0000000000010001 H
b0000000000010001 J
b0000000000010001 L
b0000000000010001 N
1O
#170000
0O
#175000
b0000000000010010 +
b0000000000010010 ,
b0000000000010010 ?
b0000000000010010 @
b0000000000010010 B
b0000000000010010 D
b0000000000010010 F
b0000000000010010 H
b0000000000010010 J
b0000000000010010 L
b0000000000010010 N
1O
#180000
0O
#185000
b0000000000010011 +
b0000000000010011 ,
b0000000000010011 ?
b0000000000010011 @
b0000000000010011 B
b0000000000010011 D
b0000000000010011 F
b0000000000010011 H
b0000000000010011 J
b0000000000010011 L
b0000000000010011 N
1O
#190000
0O
#195000
b0000000000010100 +
b0000000000010100 ,
b0000000000010100 ?
b0000000000010100 @
b0000000000010100 B
b0000000000010100 D
b0000000000010100 F
b0000000000010100 H
b0000000000010100 J
b0000000000010100 L
b0000000000010100 N
1O
#200000
0O
#205000
b0000000000010101 +
b0000000000010101 ,
b0000000000010101 ?
b0000000000010101 @
b0000000000010101 B
b0000000000010101 D
b0000000000010101 F
b0000000000010101 H
b0000000000010101 J
b0000000000010101 L
b0000000000010101 N
1O
#210000
0O
#215000
b0000000000010110 +
b0000000000010110 ,
b0000000000010110 ?
b0000000000010110 @
b0000000000010110 B
b0000000000010110 D
b0000000000010110 F
b0000000000010110 H
b0000000000010110 J
b0000000000010110 L
b0000000000010110 N
1O
#220000
0O
#225000
b0000000000010111 +
b0000000000010111 ,
b0000000000010111 ?
b0000000000010111 @
b0000000000010111 B
b0000000000010111 D
b0000000000010111 F
b0000000000010111 H
b0000000000010111 J
b0000000000010111 L
b0000000000010111 N
1O
#230000
0O
#235000
b0000000000011000 +
b0000000000011000 ,
b0000000000011000 ?
b0000000000011000 @
b0000000000011000 B
b0000000000011000 D
b0000000000011000 F
b0000000000011000 H
b0000000000011000 J
b0000000000011000 L
b0000000000011000 N
1O
#240000
0O
#245000
b0000000000011001 +
b0000000000011001 ,
b0000000000011001 ?
b0000000000011001 @
b0000000000011001 B
b0000000000011001 D
b0000000000011001 F
b0000000000011001 H
b0000000000011001 J
b0000000000011001 L
b0000000000011001 N
1O
#250000
0O
#255000
b0000000000011010 +
b0000000000011010 ,
b0000000000011010 ?
b0000000000011010 @
b0000000000011010 B
b0000000000011010 D
b0000000000011010 F
b0000000000011010 H
b0000000000011010 J
b0000000000011010 L
b0000000000011010 N
1O
#260000
0O
#265000
b0000000000011011 +
b0000000000011011 ,
b0000000000011011 ?
b0000000000011011 @
b0000000000011011 B
b0000000000011011 D
b0000000000011011 F
b0000000000011011 H
b0000000000011011 J
b0000000000011011 L
b0000000000011011 N
1O
#270000
0O
#275000
b0000000000011100 +
b0000000000011100 ,
b0000000000011100 ?
b0000000000011100 @
b0000000000011100 B
b0000000000011100 D
b0000000000011100 F
b0000000000011100 H
b0000000000011100 J
b0000000000011100 L
b0000000000011100 N
1O
#280000
0O
#285000
b0000000000011101 +
b0000000000011101 ,
b0000000000011101 ?
b0000000000011101 @
b0000000000011101 B
b0000000000011101 D
b0000000000011101 F
b0000000000011101 H
b0000000000011101 J
b0000000000011101 L
b0000000000011101 N
1O
#290000
0O
#295000
b0000000000011110 +
b0000000000011110 ,
b0000000000011110 ?
b0000000000011110 @
b0000000000011110 B
b0000000000011110 D
b0000000000011110 F
b0000000000011110 H
b0000000000011110 J
b0000000000011110 L
b0000000000011110 N
1O
#300000
0O
#305000
b0000000000011111 +
b0000000000011111 ,
b0000000000011111 ?
b0000000000011111 @
b0000000000011111 B
b0000000000011111 D
b0000000000011111 F
b0000000000011111 H
b0000000000011111 J
b0000000000011111 L
b0000000000011111 N
1O
#310000
0O
#315000
b0000000000100000 +
b0000000000100000 ,
b0000000000100000 ?
b0000000000100000 @
b0000000000100000 B
b0000000000100000 D
b0000000000100000 F
b0000000000100000 H
b0000000000100000 J
b0000000000100000 L
b0000000000100000 N
1O
#320000
0O
#325000
b0000000000100001 +
b0000000000100001 ,
b0000000000100001 ?
b0000000000100001 @
b0000000000100001 B
b0000000000100001 D
b0000000000100001 F
b0000000000100001 H
b0000000000100001 J
b0000000000100001 L
b0000000000100001 N
1O
#330000
0O
#335000
b0000000000100010 +
b0000000000100010 ,
b0000000000100010 ?
b0000000000100010 @
b0000000000100010 B
b0000000000100010 D
b0000000000100010 F
b0000000000100010 H
b0000000000100010 J
b0000000000100010 L
b0000000000100010 N
1O
#340000
0O
#345000
b0000000000100011 +
b0000000000100011 ,
b0000000000100011 ?
b0000000000100011 @
b0000000000100011 B
b0000000000100011 D
b0000000000100011 F
b0000000000100011 H
b0000000000100011 J
b0000000000100011 L
b0000000000100011 N
1O
#350000
0O
#355000
b0000000000100100 +
b0000000000100100 ,
b0000000000100100 ?
b0000000000100100 @
b0000000000100100 B
b0000000000100100 D
b0000000000100100 F
b0000000000100100 H
b0000000000100100 J
b0000000000100100 L
b0000000000100100 N
1O
#360000
0O
#365000
b0000000000100101 +
b0000000000100101 ,
b0000000000100101 ?
b0000000000100101 @
b0000000000100101 B
b0000000000100101 D
b0000000000100101 F
b0000000000100101 H
b0000000000100101 J
b0000000000100101 L
b0000000000100101 N
1O
#370000
0O
#375000
b0000000000100110 +
b0000000000100110 ,
b0000000000100110 ?
b0000000000100110 @
b0000000000100110 B
b0000000000100110 D
b0000000000100110 F
b0000000000100110 H
b0000000000100110 J
b0000000000100110 L
b0000000000100110 N
1O
#380000
0O
#385000
b0000000000100111 +
b0000000000100111 ,
b0000000000100111 ?
b0000000000100111 @
b0000000000100111 B
b0000000000100111 D
b0000000000100111 F
b0000000000100111 H
b0000000000100111 J
b0000000000100111 L
b0000000000100111 N
1O
#390000
0O
#395000
b0000000000101000 +
b0000000000101000 ,
b0000000000101000 ?
b0000000000101000 @
b0000000000101000 B
b0000000000101000 D
b0000000000101000 F
b0000000000101000 H
b0000000000101000 J
b0000000000101000 L
b0000000000101000 N
1O
#400000
0O
#405000
b0000000000101001 +
b0000000000101001 ,
b0000000000101001 ?
b0000000000101001 @
b0000000000101001 B
b0000000000101001 D
b0000000000101001 F
b0000000000101001 H
b0000000000101001 J
b0000000000101001 L
b0000000000101001 N
1O
#410000
0O
#415000
b0000000000101010 +
b0000000000101010 ,
b0000000000101010 ?
b0000000000101010 @
b0000000000101010 B
b0000000000101010 D
b0000000000101010 F
b0000000000101010 H
b0000000000101010 J
b0000000000101010 L
b0000000000101010 N
1O
#420000
0O
#425000
b0000000000101011 +
b0000000000101011 ,
b0000000000101011 ?
b0000000000101011 @
b0000000000101011 B
b0000000000101011 D
b0000000000101011 F
b0000000000101011 H
b0000000000101011 J
b0000000000101011 L
b0000000000101011 N
1O
#430000
0O
#435000
b0000000000101100 +
b0000000000101100 ,
b0000000000101100 ?
b0000000000101100 @
b0000000000101100 B
b0000000000101100 D
b0000000000101100 F
b0000000000101100 H
b0000000000101100 J
b0000000000101100 L
b0000000000101100 N
1O
#440000
0O
#445000
b0000000000101101 +
b0000000000101101 ,
b0000000000101101 ?
b0000000000101101 @
b0000000000101101 B
b0000000000101101 D
b0000000000101101 F
b0000000000101101 H
b0000000000101101 J
b0000000000101101 L
b0000000000101101 N
1O
#450000
0O
#455000
b0000000000101110 +
b0000000000101110 ,
b0000000000101110 ?
b0000000000101110 @
b0000000000101110 B
b0000000000101110 D
b0000000000101110 F
b0000000000101110 H
b0000000000101110 J
b0000000000101110 L
b0000000000101110 N
1O
#460000
0O
#465000
b0000000000101111 +
b0000000000101111 ,
b0000000000101111 ?
b0000000000101111 @
b0000000000101111 B
b0000000000101111 D
b0000000000101111 F
b0000000000101111 H
b0000000000101111 J
b0000000000101111 L
b0000000000101111 N
1O
#470000
0O
#475000
b0000000000110000 +
b0000000000110000 ,
b0000000000110000 ?
b0000000000110000 @
b0000000000110000 B
b0000000000110000 D
b0000000000110000 F
b0000000000110000 H
b0000000000110000 J
b0000000000110000 L
b0000000000110000 N
1O
#480000
0O
#485000
b0000000000110001 +
b0000000000110001 ,
b0000000000110001 ?
b0000000000110001 @
b0000000000110001 B
b0000000000110001 D
b0000000000110001 F
b0000000000110001 H
b0000000000110001 J
b0000000000110001 L
b0000000000110001 N
1O
#490000
0O
#495000
b0000000000110010 +
b0000000000110010 ,
b0000000000110010 ?
b0000000000110010 @
b0000000000110010 B
b0000000000110010 D
b0000000000110010 F
b0000000000110010 H
b0000000000110010 J
b0000000000110010 L
b0000000000110010 N
1O
#500000
0O
#505000
b0000000000110011 +
b0000000000110011 ,
b0000000000110011 ?
b0000000000110011 @
b0000000000110011 B
b0000000000110011 D
b0000000000110011 F
b0000000000110011 H
b0000000000110011 J
b0000000000110011 L
b0000000000110011 N
1O
#510000
0O
#515000
b0000000000110100 +
b0000000000110100 ,
b0000000000110100 ?
b0000000000110100 @
b0000000000110100 B
b0000000000110100 D
b0000000000110100 F
b0000000000110100 H
b0000000000110100 J
b0000000000110100 L
b0000000000110100 N
1O
#520000
0O
#525000
b0000000000110101 +
b0000000000110101 ,
b0000000000110101 ?
b0000000000110101 @
b0000000000110101 B
b0000000000110101 D
b0000000000110101 F
b0000000000110101 H
b0000000000110101 J
b0000000000110101 L
b0000000000110101 N
1O
#530000
0O
#535000
b0000000000110110 +
b0000000000110110 ,
b0000000000110110 ?
b0000000000110110 @
b0000000000110110 B
b0000000000110110 D
b0000000000110110 F
b0000000000110110 H
b0000000000110110 J
b0000000000110110 L
b0000000000110110 N
1O
#540000
0O
#545000
b0000000000110111 +
b0000000000110111 ,
b0000000000110111 ?
b0000000000110111 @
b0000000000110111 B
b0000000000110111 D
b0000000000110111 F
b0000000000110111 H
b0000000000110111 J
b0000000000110111 L
b0000000000110111 N
1O
#550000
0O
#555000
b0000000000111000 +
b0000000000111000 ,
b0000000000111000 ?
b0000000000111000 @
b0000000000111000 B
b0000000000111000 D
b0000000000111000 F
b0000000000111000 H
b0000000000111000 J
b0000000000111000 L
b0000000000111000 N
1O
#560000
0O
#565000
b0000000000111001 +
b0000000000111001 ,
b0000000000111001 ?
b0000000000111001 @
b0000000000111001 B
b0000000000111001 D
b0000000000111001 F
b0000000000111001 H
b0000000000111001 J
b0000000000111001 L
b0000000000111001 N
1O
#570000
0O
#575000
b0000000000111010 +
b0000000000111010 ,
b0000000000111010 ?
b0000000000111010 @
b0000000000111010 B
b0000000000111010 D
b0000000000111010 F
b0000000000111010 H
b0000000000111010 J
b0000000000111010 L
b0000000000111010 N
1O
#580000
0O
#585000
b0000000000111011 +
b0000000000111011 ,
b0000000000111011 ?
b0000000000111011 @
b0000000000111011 B
b0000000000111011 D
b0000000000111011 F
b0000000000111011 H
b0000000000111011 J
b0000000000111011 L
b0000000000111011 N
1O
#590000
0O
#595000
b0000000000111100 +
b0000000000111100 ,
b0000000000111100 ?
b0000000000111100 @
b0000000000111100 B
b0000000000111100 D
b0000000000111100 F
b0000000000111100 H
b0000000000111100 J
b0000000000111100 L
b0000000000111100 N
1O
#600000
0O
