rtl/sipoUnit.v
`timescale 1ns/1ps

module sipoUnit (
    input wire data_in,
    input wire clk,
    output reg [7:0] q
);

    dff dff0 (
        .d(data_in),
        .clk(clk),
        .q(q[0])
        );
    
    dff dff1 (
        .d(q[0]),
        .clk(clk),
        .q(q[1])
        );

    dff dff2 (
        .d(q[1]),
        .clk(clk),
        .q(q[2])
        );

    dff dff3 (
        .d(q[2]),
        .clk(clk),
        .q(q[3])
        );

    dff dff4 (
        .d(q[3]),
        .clk(clk),
        .q(q[4])
        );

    dff dff5 (
        .d(q[4]),
        .clk(clk),
        .q(q[5])
        );

    dff dff6 (
        .d(q[5]),
        .clk(clk),
        .q(q[6])
        );

    dff dff7 (
        .d(q[6]),
        .clk(clk),
        .q(q[7])
        );
endmodule

module dff (
    input d,
    input clk,
    output reg q
);

always @ (posedge clk or negedge clk) begin
    q <= d;
end
    
endmodule

tb/sipoTest.v
`timescale 1ns/1ps

module sipoTest;

reg clk;
reg data;
reg [7:0] q;

    sipoUnit dut (
        .data_in(data),
        .clk(clk),
        .q(q)
    );

    always #5 clk = ~clk;

    initial begin
        data = 0;
        clk = 0;
        $dumpfile("sipoDump.vcd");
        $dumpvars;
        $display("time=%0tps", $time);
        $display("input=%0h", data);
        $display("output=%0h", q[7], q[6], q[5], q[4], q[3], q[2], q[1], q[0]);
        $display("---");
        #5 data = 1;
        $display("time=%0tps", $time);
        $display("input=%0h", data);
        $display("output=%0h", q[7], q[6], q[5], q[4], q[3], q[2], q[1], q[0]);
        $display("---");
        #5 data = 0;
        $display("time=%0tps", $time);
        $display("input=%0h", data);
        $display("output=%0h", q[7], q[6], q[5], q[4], q[3], q[2], q[1], q[0]);
        $display("---");
        #5 data = 0;
        $display("time=%0tps", $time);
        $display("input=%0h", data);
        $display("output=%0h", q[7], q[6], q[5], q[4], q[3], q[2], q[1], q[0]);
        $display("---");
        #5 data = 1;
        $display("time=%0tps", $time);
        $display("input=%0h", data);
        $display("output=%0h", q[7], q[6], q[5], q[4], q[3], q[2], q[1], q[0]);
        $display("---");
        #5 data = 1;
        $display("input=%0h", data);
        $display("output=%0h", q[7], q[6], q[5], q[4], q[3], q[2], q[1], q[0]);
        $display("---");
        $display("time=%0tps", $time);
        #5 data = 0;
        $display("time=%0tps", $time);
        $display("input=%0h", data);
        $display("output=%0h", q[7], q[6], q[5], q[4], q[3], q[2], q[1], q[0]);
        $display("---");
        #5 data = 0;
        $display("time=%0tps", $time);
        $display("input=%0h", data);
        $display("output=%0h", q[7], q[6], q[5], q[4], q[3], q[2], q[1], q[0]);
        $display("---");
        #5 data = 1;
        $display("time=%0tps", $time);
        $display("input=%0h", data);
        $display("output=%0h", q[7], q[6], q[5], q[4], q[3], q[2], q[1], q[0]);
        $display("---");
        #5;
        $display("time=%0tps", $time);
        $display("input=%0h", data);
        $display("output=%0h", q[7], q[6], q[5], q[4], q[3], q[2], q[1], q[0]);
        $display("---");
        $finish;
    end
endmodule

sim/waveforms/sipoDump.vcd
$version Generated by VerilatedVcd $end
$timescale 1ps $end
 $scope module TOP $end
  $scope module sipoTest $end
   $var wire 1 , clk $end
   $var wire 1 - data $end
   $var wire 8 # q [7:0] $end
   $scope module dut $end
    $var wire 1 - data_in $end
    $var wire 1 , clk $end
    $var wire 8 # q [7:0] $end
    $scope module dff0 $end
     $var wire 1 - d $end
     $var wire 1 , clk $end
     $var wire 1 $ q $end
    $upscope $end
    $scope module dff1 $end
     $var wire 1 $ d $end
     $var wire 1 , clk $end
     $var wire 1 % q $end
    $upscope $end
    $scope module dff2 $end
     $var wire 1 % d $end
     $var wire 1 , clk $end
     $var wire 1 & q $end
    $upscope $end
    $scope module dff3 $end
     $var wire 1 & d $end
     $var wire 1 , clk $end
     $var wire 1 ' q $end
    $upscope $end
    $scope module dff4 $end
     $var wire 1 ' d $end
     $var wire 1 , clk $end
     $var wire 1 ( q $end
    $upscope $end
    $scope module dff5 $end
     $var wire 1 ( d $end
     $var wire 1 , clk $end
     $var wire 1 ) q $end
    $upscope $end
    $scope module dff6 $end
     $var wire 1 ) d $end
     $var wire 1 , clk $end
     $var wire 1 * q $end
    $upscope $end
    $scope module dff7 $end
     $var wire 1 * d $end
     $var wire 1 , clk $end
     $var wire 1 + q $end
    $upscope $end
   $upscope $end
  $upscope $end
 $upscope $end
$enddefinitions $end


#0
b00000000 #
0$
0%
0&
0'
0(
0)
0*
0+
0,
0-
#5000
b00000001 #
1$
1,
1-
#10000
b00000010 #
0$
1%
0,
0-
#15000
b00000100 #
0%
1&
1,
#20000
b00001001 #
1$
0&
1'
0,
1-
#25000
b00010011 #
1%
0'
1(
1,
#30000
b00100110 #
0$
1&
0(
1)
0,
0-
#35000
b01001100 #
0%
1'
0)
1*
1,
#40000
b10011001 #
1$
0&
1(
0*
1+
0,
1-
#45000
b00110011 #
1%
0'
1)
0+
1,
