rtl/sipoUnit.v
`timescale 1ns/1ps

module sipoUnit (
    input wire data_in,
    input reg reset,
    input wire clk,
    output reg [7:0] q
);

    dff dff0 (
        .d(data_in),
        .reset(reset),
        .clk(clk),
        .q(q[0])
        );

    generate
        for (genvar i = 0; i < 7; i++) begin
            dff dff_inst (
                .d(q[i]),
                .reset(reset),
                .clk(clk),
                .q(q[i+1])
            );
        end
    endgenerate
endmodule

module dff (
    input d,
    input clk,
    input reg reset,
    output reg q
);

always @ (posedge clk or negedge clk) begin
    if (reset) begin
        q <= 1'b0;
    end else begin
        q <= d;
    end
end
    
endmodule

tb/sipoTest.v
`timescale 1ns/1ps

module sipoTest;

reg clk;
reg data;
reg reset;
reg [7:0] q;

    sipoUnit dut (
        .data_in(data),
        .reset(reset),
        .clk(clk),
        .q(q)
    );

    always #5 clk = ~clk;
    always if (reset) begin data = 1'b0; end

    initial begin
        data = 0;
        clk = 0;
        $dumpfile("sipoDump.vcd");
        $dumpvars;
        $display("time=%0tps", $time);
        $display("input=%0h", data);
        $display("output=%0h", q[7], q[6], q[5], q[4], q[3], q[2], q[1], q[0]);
        $display("---");
        #5 data = 1;
        $display("time=%0tps", $time);
        $display("input=%0h", data);
        $display("output=%0h", q[7], q[6], q[5], q[4], q[3], q[2], q[1], q[0]);
        $display("---");
        #5 data = 0;
        $display("time=%0tps", $time);
        $display("input=%0h", data);
        $display("output=%0h", q[7], q[6], q[5], q[4], q[3], q[2], q[1], q[0]);
        $display("---");
        #5 data = 0;
        $display("time=%0tps", $time);
        $display("input=%0h", data);
        $display("output=%0h", q[7], q[6], q[5], q[4], q[3], q[2], q[1], q[0]);
        $display("---");
        #5 data = 1;
        $display("time=%0tps", $time);
        $display("input=%0h", data);
        $display("output=%0h", q[7], q[6], q[5], q[4], q[3], q[2], q[1], q[0]);
        $display("---");
        #5 data = 1;
        $display("input=%0h", data);
        $display("output=%0h", q[7], q[6], q[5], q[4], q[3], q[2], q[1], q[0]);
        $display("---");
        $display("time=%0tps", $time);
        #5 data = 0;
        $display("time=%0tps", $time);
        $display("input=%0h", data);
        $display("output=%0h", q[7], q[6], q[5], q[4], q[3], q[2], q[1], q[0]);
        $display("---");
        #5 data = 0;
        $display("time=%0tps", $time);
        $display("input=%0h", data);
        $display("output=%0h", q[7], q[6], q[5], q[4], q[3], q[2], q[1], q[0]);
        $display("---");
        #5 data = 1;
        $display("time=%0tps", $time);
        $display("input=%0h", data);
        $display("output=%0h", q[7], q[6], q[5], q[4], q[3], q[2], q[1], q[0]);
        $display("---");
        #5;
        $display("time=%0tps", $time);
        $display("input=%0h", data);
        $display("output=%0h", q[7], q[6], q[5], q[4], q[3], q[2], q[1], q[0]);
        $display("---");
        reset = 1;
        #5;
        $display("time=%0tps", $time);
        $display("input=%0h", data);
        $display("output=%0h", q[7], q[6], q[5], q[4], q[3], q[2], q[1], q[0]);
        $display("---");

        $finish;
    end
endmodule

sim/waveforms/sipoDump.vcd
$version Generated by VerilatedVcd $end
$timescale 1ps $end
 $scope module TOP $end
  $scope module sipoTest $end
   $var wire 1 , clk $end
   $var wire 1 - data $end
   $var wire 1 . reset $end
   $var wire 8 # q [7:0] $end
   $scope module dut $end
    $var wire 1 - data_in $end
    $var wire 1 . reset $end
    $var wire 1 , clk $end
    $var wire 8 # q [7:0] $end
    $scope module dff0 $end
     $var wire 1 - d $end
     $var wire 1 , clk $end
     $var wire 1 . reset $end
     $var wire 1 $ q $end
    $upscope $end
    $scope module genblk1[0] $end
     $scope module dff_inst $end
      $var wire 1 $ d $end
      $var wire 1 , clk $end
      $var wire 1 . reset $end
      $var wire 1 % q $end
     $upscope $end
    $upscope $end
    $scope module genblk1[1] $end
     $scope module dff_inst $end
      $var wire 1 % d $end
      $var wire 1 , clk $end
      $var wire 1 . reset $end
      $var wire 1 & q $end
     $upscope $end
    $upscope $end
    $scope module genblk1[2] $end
     $scope module dff_inst $end
      $var wire 1 & d $end
      $var wire 1 , clk $end
      $var wire 1 . reset $end
      $var wire 1 ' q $end
     $upscope $end
    $upscope $end
    $scope module genblk1[3] $end
     $scope module dff_inst $end
      $var wire 1 ' d $end
      $var wire 1 , clk $end
      $var wire 1 . reset $end
      $var wire 1 ( q $end
     $upscope $end
    $upscope $end
    $scope module genblk1[4] $end
     $scope module dff_inst $end
      $var wire 1 ( d $end
      $var wire 1 , clk $end
      $var wire 1 . reset $end
      $var wire 1 ) q $end
     $upscope $end
    $upscope $end
    $scope module genblk1[5] $end
     $scope module dff_inst $end
      $var wire 1 ) d $end
      $var wire 1 , clk $end
      $var wire 1 . reset $end
      $var wire 1 * q $end
     $upscope $end
    $upscope $end
    $scope module genblk1[6] $end
     $scope module dff_inst $end
      $var wire 1 * d $end
      $var wire 1 , clk $end
      $var wire 1 . reset $end
      $var wire 1 + q $end
     $upscope $end
    $upscope $end
   $upscope $end
  $upscope $end
 $upscope $end
$enddefinitions $end


#0
b00000000 #
0$
0%
0&
0'
0(
0)
0*
0+
0,
0-
0.
#5000
b00000001 #
1$
1,
1-
#10000
b00000010 #
0$
1%
0,
0-
#15000
b00000100 #
0%
1&
1,
#20000
b00001001 #
1$
0&
1'
0,
1-
#25000
b00010011 #
1%
0'
1(
1,
#30000
b00100110 #
0$
1&
0(
1)
0,
0-
#35000
b01001100 #
0%
1'
0)
1*
1,
#40000
b10011001 #
1$
0&
1(
0*
1+
0,
1-
#45000
b00000000 #
0$
0'
0(
0+
1,
0-
1.
