rtl/baudUnit.v
`timescale 1ns/1ps

module baudUnit (
    input clk,
    input reset,
    output reg baud
);

parameter SYSTEM_CLOCK_FREQ = 100000000; // 100 MHz
parameter BAUD_RATE = 115200;

localparam int DIVIDER = SYSTEM_CLOCK_FREQ / BAUD_RATE;

reg [15:0] counter;

always @(posedge clk or posedge reset) begin
    if (reset) begin
        counter <= 0;
        baud <= 0;
    end else if (counter >= DIVIDER - 1) begin
        counter <= 0;
        baud <= ~baud;
    end else begin
        counter <= counter + 1;
    end
end

endmodule

rtl/pisoUnit.v
`timescale 1ns/1ps

module pisoUnit #(parameter WIDTH = 8) (
    input clk,
    input [WIDTH-1:0] data,
    input reset,
    input start,
    output reg baud,
    output reg [3:0] shift_counter,
    output reg q
);

    parameter MAX_WIDTH = WIDTH + 2;
    
    reg [WIDTH+1:0] shift_reg;
    reg baud_toggle;
    reg start_toggle;
    assign baud_edge = baud & (~baud_toggle);
    assign start_edge = start & (~start_toggle);

    baudUnit dut (
        .clk(clk),
        .reset(reset),
        .baud(baud)
    );

    always @ (posedge clk or posedge reset) begin
        if (reset) begin
            q <= 1;
            shift_reg <= 1;
            shift_counter <= 0;
        end else begin
            baud_toggle <= baud;
            start_toggle <= start;
        end if (shift_reg == 0) begin
            q <= 1;
        end if (start_edge) begin
            shift_reg <= {1'b1, data, 1'b0};
        end if (baud_edge) begin
            q <= shift_reg[0];
            shift_reg <= shift_reg >> 1;
            if (shift_counter < MAX_WIDTH) begin
                shift_counter <= shift_counter + 1;
            end else begin
                shift_counter <= 0;
            end if (shift_reg == 0) begin
                q <= 1;
            end
        end
    end

endmodule

rtl/transmitter.v
`timescale 1ns/1ps

module transmitter #(parameter WIDTH = 8) (
        input clk,
        input [7:0] data,
        input reset,
        output baud,
        output tx,
        output [3:0] bit_count,
        output start
    );

    pisoUnit piso (
        .clk(clk),
        .reset(reset),
        .data(data),
        .shift_counter(bit_count),
        .q(tx),
        .start(start)
    );
    
    baudUnit baudGen (
        .clk(clk),
        .baud(baud),
        .reset(reset)
    );

endmodule

tb/transmitter_tb.v
`timescale 1ns/1ps

module transmitter_tb;

parameter WIDTH = 8;

reg clk;
reg reset;
wire baud;
wire tx;
reg [WIDTH-1:0] data;
wire [3:0] bit_count;
reg start;

// Instantiate the transmitter module
transmitter dut (
    .clk(clk),
    .reset(reset),
    .baud(baud),
    .data(data),
    .bit_count(bit_count),
    .tx(tx),
    .start(start)
);

// Clock generation
always #5 clk = ~clk;  // clock period = 10ns

initial begin
    // Simulation setup
    clk = 0;
    data = 8'b0;
    start = 0;
    reset = 0;

    $dumpfile("txDump.vcd");
    $dumpvars(0, transmitter_tb);

    // Test header
    $display("Time | Data (Input) | TX (Output) | Bit Count");
    $display("-------------------------------------------------------------");

    // Test case #1: Transmitting 8'b10011001
    #10 data = 8'b10011001;
    #10 start = 1;
    $display("Sending Data Block #1 (10011001)");
    
    repeat (10) begin
        #17355;  // Simulate a period for the baud rate, adjust based on actual baud rate
        $display("%0tps | 0x%h | %b | %d", $time, data, tx, bit_count);
    end

    // Reset the system
    reset_sequence();

    // Test case #2: Transmitting 8'b01110000
    #10 data = 8'b01110000;
    #20 start = 1;
    $display("Sending Data Block #2 (01110000)");
    
    repeat (10) begin
        #17355;
        $display("%0tps | 0x%h | %b | %d", $time, data, tx, bit_count);
    end

    // Final reset before ending the simulation
    reset_sequence();

    // Finish simulation after final delay
    #100000 $finish;
end

// Task to handle reset
task reset_sequence;
    begin
        reset = 1;
        start = 0;
        #5 reset = 0;
    end
endtask

endmodule

sim/waveforms/txDump.vcd
$version Generated by VerilatedVcd $end
$timescale 1ps $end
 $scope module TOP $end
  $scope module transmitter_tb $end
   $var wire 32 2 WIDTH [31:0] $end
   $var wire 1 - clk $end
   $var wire 1 . reset $end
   $var wire 1 # baud $end
   $var wire 1 $ tx $end
   $var wire 8 / data [7:0] $end
   $var wire 4 % bit_count [3:0] $end
   $var wire 1 0 start $end
   $scope module dut $end
    $var wire 32 2 WIDTH [31:0] $end
    $var wire 1 - clk $end
    $var wire 8 / data [7:0] $end
    $var wire 1 . reset $end
    $var wire 1 # baud $end
    $var wire 1 $ tx $end
    $var wire 4 % bit_count [3:0] $end
    $var wire 1 0 start $end
    $scope module baudGen $end
     $var wire 1 - clk $end
     $var wire 1 . reset $end
     $var wire 1 # baud $end
     $var wire 32 3 SYSTEM_CLOCK_FREQ [31:0] $end
     $var wire 32 4 BAUD_RATE [31:0] $end
     $var wire 32 5 DIVIDER [31:0] $end
     $var wire 16 & counter [15:0] $end
    $upscope $end
    $scope module piso $end
     $var wire 32 2 WIDTH [31:0] $end
     $var wire 1 - clk $end
     $var wire 8 / data [7:0] $end
     $var wire 1 . reset $end
     $var wire 1 0 start $end
     $var wire 1 ' baud $end
     $var wire 4 % shift_counter [3:0] $end
     $var wire 1 $ q $end
     $var wire 32 6 MAX_WIDTH [31:0] $end
     $var wire 10 ( shift_reg [9:0] $end
     $var wire 1 ) baud_toggle $end
     $var wire 1 * start_toggle $end
     $var wire 1 + baud_edge $end
     $var wire 1 1 start_edge $end
     $scope module dut $end
      $var wire 1 - clk $end
      $var wire 1 . reset $end
      $var wire 1 ' baud $end
      $var wire 32 3 SYSTEM_CLOCK_FREQ [31:0] $end
      $var wire 32 4 BAUD_RATE [31:0] $end
      $var wire 32 5 DIVIDER [31:0] $end
      $var wire 16 , counter [15:0] $end
     $upscope $end
    $upscope $end
   $upscope $end
  $upscope $end
 $upscope $end
$enddefinitions $end


#0
0#
0$
b0000 %
b0000000000000000 &
0'
b0000000000 (
0)
0*
0+
b0000000000000000 ,
0-
0.
b00000000 /
00
01
b00000000000000000000000000001000 2
b00000101111101011110000100000000 3
b00000000000000011100001000000000 4
b00000000000000000000001101100100 5
b00000000000000000000000000001010 6
#5000
1$
b0000000000000001 &
b0000000000000001 ,
1-
#10000
0-
b10011001 /
#15000
b0000000000000010 &
b0000000000000010 ,
1-
#20000
0-
10
11
#25000
b0000000000000011 &
b1100110010 (
1*
b0000000000000011 ,
1-
01
#30000
0-
#35000
b0000000000000100 &
b0000000000000100 ,
1-
#40000
0-
#45000
b0000000000000101 &
b0000000000000101 ,
1-
#50000
0-
#55000
b0000000000000110 &
b0000000000000110 ,
1-
#60000
0-
#65000
b0000000000000111 &
b0000000000000111 ,
1-
#70000
0-
#75000
b0000000000001000 &
b0000000000001000 ,
1-
#80000
0-
#85000
b0000000000001001 &
b0000000000001001 ,
1-
#90000
0-
#95000
b0000000000001010 &
b0000000000001010 ,
1-
#100000
0-
#105000
b0000000000001011 &
b0000000000001011 ,
1-
#110000
0-
#115000
b0000000000001100 &
b0000000000001100 ,
1-
#120000
0-
#125000
b0000000000001101 &
b0000000000001101 ,
1-
#130000
0-
#135000
b0000000000001110 &
b0000000000001110 ,
1-
#140000
0-
#145000
b0000000000001111 &
b0000000000001111 ,
1-
#150000
0-
#155000
b0000000000010000 &
b0000000000010000 ,
1-
#160000
0-
#165000
b0000000000010001 &
b0000000000010001 ,
1-
#170000
0-
#175000
b0000000000010010 &
b0000000000010010 ,
1-
#180000
0-
#185000
b0000000000010011 &
b0000000000010011 ,
1-
#190000
0-
#195000
b0000000000010100 &
b0000000000010100 ,
1-
#200000
0-
#205000
b0000000000010101 &
b0000000000010101 ,
1-
#210000
0-
#215000
b0000000000010110 &
b0000000000010110 ,
1-
#220000
0-
#225000
b0000000000010111 &
b0000000000010111 ,
1-
#230000
0-
#235000
b0000000000011000 &
b0000000000011000 ,
1-
#240000
0-
#245000
b0000000000011001 &
b0000000000011001 ,
1-
#250000
0-
#255000
b0000000000011010 &
b0000000000011010 ,
1-
#260000
0-
#265000
b0000000000011011 &
b0000000000011011 ,
1-
#270000
0-
#275000
b0000000000011100 &
b0000000000011100 ,
1-
#280000
0-
#285000
b0000000000011101 &
b0000000000011101 ,
1-
#290000
0-
#295000
b0000000000011110 &
b0000000000011110 ,
1-
#300000
0-
#305000
b0000000000011111 &
b0000000000011111 ,
1-
#310000
0-
#315000
b0000000000100000 &
b0000000000100000 ,
1-
#320000
0-
#325000
b0000000000100001 &
b0000000000100001 ,
1-
#330000
0-
#335000
b0000000000100010 &
b0000000000100010 ,
1-
#340000
0-
#345000
b0000000000100011 &
b0000000000100011 ,
1-
#350000
0-
#355000
b0000000000100100 &
b0000000000100100 ,
1-
#360000
0-
#365000
b0000000000100101 &
b0000000000100101 ,
1-
#370000
0-
#375000
b0000000000100110 &
b0000000000100110 ,
1-
#380000
0-
#385000
b0000000000100111 &
b0000000000100111 ,
1-
#390000
0-
#395000
b0000000000101000 &
b0000000000101000 ,
1-
#400000
0-
#405000
b0000000000101001 &
b0000000000101001 ,
1-
#410000
0-
#415000
b0000000000101010 &
b0000000000101010 ,
1-
#420000
0-
#425000
b0000000000101011 &
b0000000000101011 ,
1-
#430000
0-
#435000
b0000000000101100 &
b0000000000101100 ,
1-
#440000
0-
#445000
b0000000000101101 &
b0000000000101101 ,
1-
#450000
0-
#455000
b0000000000101110 &
b0000000000101110 ,
1-
#460000
0-
#465000
b0000000000101111 &
b0000000000101111 ,
1-
#470000
0-
#475000
b0000000000110000 &
b0000000000110000 ,
1-
#480000
0-
#485000
b0000000000110001 &
b0000000000110001 ,
1-
#490000
0-
#495000
b0000000000110010 &
b0000000000110010 ,
1-
#500000
0-
#505000
b0000000000110011 &
b0000000000110011 ,
1-
#510000
0-
#515000
b0000000000110100 &
b0000000000110100 ,
1-
#520000
0-
#525000
b0000000000110101 &
b0000000000110101 ,
1-
#530000
0-
#535000
b0000000000110110 &
b0000000000110110 ,
1-
#540000
0-
#545000
b0000000000110111 &
b0000000000110111 ,
1-
#550000
0-
#555000
b0000000000111000 &
b0000000000111000 ,
1-
#560000
0-
#565000
b0000000000111001 &
b0000000000111001 ,
1-
#570000
0-
#575000
b0000000000111010 &
b0000000000111010 ,
1-
#580000
0-
#585000
b0000000000111011 &
b0000000000111011 ,
1-
#590000
0-
#595000
b0000000000111100 &
b0000000000111100 ,
1-
#600000
0-
#605000
b0000000000111101 &
b0000000000111101 ,
1-
#610000
0-
#615000
b0000000000111110 &
b0000000000111110 ,
1-
#620000
0-
#625000
b0000000000111111 &
b0000000000111111 ,
1-
#630000
0-
#635000
b0000000001000000 &
b0000000001000000 ,
1-
#640000
0-
#645000
b0000000001000001 &
b0000000001000001 ,
1-
#650000
0-
#655000
b0000000001000010 &
b0000000001000010 ,
1-
#660000
0-
#665000
b0000000001000011 &
b0000000001000011 ,
1-
#670000
0-
#675000
b0000000001000100 &
b0000000001000100 ,
1-
#680000
0-
#685000
b0000000001000101 &
b0000000001000101 ,
1-
#690000
0-
#695000
b0000000001000110 &
b0000000001000110 ,
1-
#700000
0-
#705000
b0000000001000111 &
b0000000001000111 ,
1-
#710000
0-
#715000
b0000000001001000 &
b0000000001001000 ,
1-
#720000
0-
#725000
b0000000001001001 &
b0000000001001001 ,
1-
#730000
0-
#735000
b0000000001001010 &
b0000000001001010 ,
1-
#740000
0-
#745000
b0000000001001011 &
b0000000001001011 ,
1-
#750000
0-
#755000
b0000000001001100 &
b0000000001001100 ,
1-
#760000
0-
#765000
b0000000001001101 &
b0000000001001101 ,
1-
#770000
0-
#775000
b0000000001001110 &
b0000000001001110 ,
1-
#780000
0-
#785000
b0000000001001111 &
b0000000001001111 ,
1-
#790000
0-
#795000
b0000000001010000 &
b0000000001010000 ,
1-
#800000
0-
#805000
b0000000001010001 &
b0000000001010001 ,
1-
#810000
0-
#815000
b0000000001010010 &
b0000000001010010 ,
1-
#820000
0-
#825000
b0000000001010011 &
b0000000001010011 ,
1-
#830000
0-
#835000
b0000000001010100 &
b0000000001010100 ,
1-
#840000
0-
#845000
b0000000001010101 &
b0000000001010101 ,
1-
#850000
0-
#855000
b0000000001010110 &
b0000000001010110 ,
1-
#860000
0-
#865000
b0000000001010111 &
b0000000001010111 ,
1-
#870000
0-
#875000
b0000000001011000 &
b0000000001011000 ,
1-
#880000
0-
#885000
b0000000001011001 &
b0000000001011001 ,
1-
#890000
0-
#895000
b0000000001011010 &
b0000000001011010 ,
1-
#900000
0-
#905000
b0000000001011011 &
b0000000001011011 ,
1-
#910000
0-
#915000
b0000000001011100 &
b0000000001011100 ,
1-
#920000
0-
#925000
b0000000001011101 &
b0000000001011101 ,
1-
#930000
0-
#935000
b0000000001011110 &
b0000000001011110 ,
1-
#940000
0-
#945000
b0000000001011111 &
b0000000001011111 ,
1-
#950000
0-
#955000
b0000000001100000 &
b0000000001100000 ,
1-
#960000
0-
#965000
b0000000001100001 &
b0000000001100001 ,
1-
#970000
0-
#975000
b0000000001100010 &
b0000000001100010 ,
1-
#980000
0-
#985000
b0000000001100011 &
b0000000001100011 ,
1-
#990000
0-
#995000
b0000000001100100 &
b0000000001100100 ,
1-
#1000000
0-
#1005000
b0000000001100101 &
b0000000001100101 ,
1-
#1010000
0-
#1015000
b0000000001100110 &
b0000000001100110 ,
1-
#1020000
0-
#1025000
b0000000001100111 &
b0000000001100111 ,
1-
#1030000
0-
#1035000
b0000000001101000 &
b0000000001101000 ,
1-
#1040000
0-
#1045000
b0000000001101001 &
b0000000001101001 ,
1-
#1050000
0-
#1055000
b0000000001101010 &
b0000000001101010 ,
1-
#1060000
0-
#1065000
b0000000001101011 &
b0000000001101011 ,
1-
#1070000
0-
#1075000
b0000000001101100 &
b0000000001101100 ,
1-
#1080000
0-
#1085000
b0000000001101101 &
b0000000001101101 ,
1-
#1090000
0-
#1095000
b0000000001101110 &
b0000000001101110 ,
1-
#1100000
0-
#1105000
b0000000001101111 &
b0000000001101111 ,
1-
#1110000
0-
#1115000
b0000000001110000 &
b0000000001110000 ,
1-
#1120000
0-
#1125000
b0000000001110001 &
b0000000001110001 ,
1-
#1130000
0-
#1135000
b0000000001110010 &
b0000000001110010 ,
1-
#1140000
0-
#1145000
b0000000001110011 &
b0000000001110011 ,
1-
#1150000
0-
#1155000
b0000000001110100 &
b0000000001110100 ,
1-
#1160000
0-
#1165000
b0000000001110101 &
b0000000001110101 ,
1-
#1170000
0-
#1175000
b0000000001110110 &
b0000000001110110 ,
1-
#1180000
0-
#1185000
b0000000001110111 &
b0000000001110111 ,
1-
#1190000
0-
#1195000
b0000000001111000 &
b0000000001111000 ,
1-
#1200000
0-
#1205000
b0000000001111001 &
b0000000001111001 ,
1-
#1210000
0-
#1215000
b0000000001111010 &
b0000000001111010 ,
1-
#1220000
0-
#1225000
b0000000001111011 &
b0000000001111011 ,
1-
#1230000
0-
#1235000
b0000000001111100 &
b0000000001111100 ,
1-
#1240000
0-
#1245000
b0000000001111101 &
b0000000001111101 ,
1-
#1250000
0-
#1255000
b0000000001111110 &
b0000000001111110 ,
1-
#1260000
0-
#1265000
b0000000001111111 &
b0000000001111111 ,
1-
#1270000
0-
#1275000
b0000000010000000 &
b0000000010000000 ,
1-
#1280000
0-
#1285000
b0000000010000001 &
b0000000010000001 ,
1-
#1290000
0-
#1295000
b0000000010000010 &
b0000000010000010 ,
1-
#1300000
0-
#1305000
b0000000010000011 &
b0000000010000011 ,
1-
#1310000
0-
#1315000
b0000000010000100 &
b0000000010000100 ,
1-
#1320000
0-
#1325000
b0000000010000101 &
b0000000010000101 ,
1-
#1330000
0-
#1335000
b0000000010000110 &
b0000000010000110 ,
1-
#1340000
0-
#1345000
b0000000010000111 &
b0000000010000111 ,
1-
#1350000
0-
#1355000
b0000000010001000 &
b0000000010001000 ,
1-
#1360000
0-
#1365000
b0000000010001001 &
b0000000010001001 ,
1-
#1370000
0-
#1375000
b0000000010001010 &
b0000000010001010 ,
1-
#1380000
0-
#1385000
b0000000010001011 &
b0000000010001011 ,
1-
#1390000
0-
#1395000
b0000000010001100 &
b0000000010001100 ,
1-
#1400000
0-
#1405000
b0000000010001101 &
b0000000010001101 ,
1-
#1410000
0-
#1415000
b0000000010001110 &
b0000000010001110 ,
1-
#1420000
0-
#1425000
b0000000010001111 &
b0000000010001111 ,
1-
#1430000
0-
#1435000
b0000000010010000 &
b0000000010010000 ,
1-
#1440000
0-
#1445000
b0000000010010001 &
b0000000010010001 ,
1-
#1450000
0-
#1455000
b0000000010010010 &
b0000000010010010 ,
1-
#1460000
0-
#1465000
b0000000010010011 &
b0000000010010011 ,
1-
#1470000
0-
#1475000
b0000000010010100 &
b0000000010010100 ,
1-
#1480000
0-
#1485000
b0000000010010101 &
b0000000010010101 ,
1-
#1490000
0-
#1495000
b0000000010010110 &
b0000000010010110 ,
1-
#1500000
0-
#1505000
b0000000010010111 &
b0000000010010111 ,
1-
#1510000
0-
#1515000
b0000000010011000 &
b0000000010011000 ,
1-
#1520000
0-
#1525000
b0000000010011001 &
b0000000010011001 ,
1-
#1530000
0-
#1535000
b0000000010011010 &
b0000000010011010 ,
1-
#1540000
0-
#1545000
b0000000010011011 &
b0000000010011011 ,
1-
#1550000
0-
#1555000
b0000000010011100 &
b0000000010011100 ,
1-
#1560000
0-
#1565000
b0000000010011101 &
b0000000010011101 ,
1-
#1570000
0-
#1575000
b0000000010011110 &
b0000000010011110 ,
1-
#1580000
0-
#1585000
b0000000010011111 &
b0000000010011111 ,
1-
#1590000
0-
#1595000
b0000000010100000 &
b0000000010100000 ,
1-
#1600000
0-
#1605000
b0000000010100001 &
b0000000010100001 ,
1-
#1610000
0-
#1615000
b0000000010100010 &
b0000000010100010 ,
1-
#1620000
0-
#1625000
b0000000010100011 &
b0000000010100011 ,
1-
#1630000
0-
#1635000
b0000000010100100 &
b0000000010100100 ,
1-
#1640000
0-
#1645000
b0000000010100101 &
b0000000010100101 ,
1-
#1650000
0-
#1655000
b0000000010100110 &
b0000000010100110 ,
1-
#1660000
0-
#1665000
b0000000010100111 &
b0000000010100111 ,
1-
#1670000
0-
#1675000
b0000000010101000 &
b0000000010101000 ,
1-
#1680000
0-
#1685000
b0000000010101001 &
b0000000010101001 ,
1-
#1690000
0-
#1695000
b0000000010101010 &
b0000000010101010 ,
1-
#1700000
0-
#1705000
b0000000010101011 &
b0000000010101011 ,
1-
#1710000
0-
#1715000
b0000000010101100 &
b0000000010101100 ,
1-
#1720000
0-
#1725000
b0000000010101101 &
b0000000010101101 ,
1-
#1730000
0-
#1735000
b0000000010101110 &
b0000000010101110 ,
1-
#1740000
0-
#1745000
b0000000010101111 &
b0000000010101111 ,
1-
#1750000
0-
#1755000
b0000000010110000 &
b0000000010110000 ,
1-
#1760000
0-
#1765000
b0000000010110001 &
b0000000010110001 ,
1-
#1770000
0-
#1775000
b0000000010110010 &
b0000000010110010 ,
1-
#1780000
0-
#1785000
b0000000010110011 &
b0000000010110011 ,
1-
#1790000
0-
#1795000
b0000000010110100 &
b0000000010110100 ,
1-
#1800000
0-
#1805000
b0000000010110101 &
b0000000010110101 ,
1-
#1810000
0-
#1815000
b0000000010110110 &
b0000000010110110 ,
1-
#1820000
0-
#1825000
b0000000010110111 &
b0000000010110111 ,
1-
#1830000
0-
#1835000
b0000000010111000 &
b0000000010111000 ,
1-
#1840000
0-
#1845000
b0000000010111001 &
b0000000010111001 ,
1-
#1850000
0-
#1855000
b0000000010111010 &
b0000000010111010 ,
1-
#1860000
0-
#1865000
b0000000010111011 &
b0000000010111011 ,
1-
#1870000
0-
#1875000
b0000000010111100 &
b0000000010111100 ,
1-
#1880000
0-
#1885000
b0000000010111101 &
b0000000010111101 ,
1-
#1890000
0-
#1895000
b0000000010111110 &
b0000000010111110 ,
1-
#1900000
0-
#1905000
b0000000010111111 &
b0000000010111111 ,
1-
#1910000
0-
#1915000
b0000000011000000 &
b0000000011000000 ,
1-
#1920000
0-
#1925000
b0000000011000001 &
b0000000011000001 ,
1-
#1930000
0-
#1935000
b0000000011000010 &
b0000000011000010 ,
1-
#1940000
0-
#1945000
b0000000011000011 &
b0000000011000011 ,
1-
#1950000
0-
#1955000
b0000000011000100 &
b0000000011000100 ,
1-
#1960000
0-
#1965000
b0000000011000101 &
b0000000011000101 ,
1-
#1970000
0-
#1975000
b0000000011000110 &
b0000000011000110 ,
1-
#1980000
0-
#1985000
b0000000011000111 &
b0000000011000111 ,
1-
#1990000
0-
#1995000
b0000000011001000 &
b0000000011001000 ,
1-
#2000000
0-
#2005000
b0000000011001001 &
b0000000011001001 ,
1-
#2010000
0-
#2015000
b0000000011001010 &
b0000000011001010 ,
1-
#2020000
0-
#2025000
b0000000011001011 &
b0000000011001011 ,
1-
#2030000
0-
#2035000
b0000000011001100 &
b0000000011001100 ,
1-
#2040000
0-
#2045000
b0000000011001101 &
b0000000011001101 ,
1-
#2050000
0-
#2055000
b0000000011001110 &
b0000000011001110 ,
1-
#2060000
0-
#2065000
b0000000011001111 &
b0000000011001111 ,
1-
#2070000
0-
#2075000
b0000000011010000 &
b0000000011010000 ,
1-
#2080000
0-
#2085000
b0000000011010001 &
b0000000011010001 ,
1-
#2090000
0-
#2095000
b0000000011010010 &
b0000000011010010 ,
1-
#2100000
0-
#2105000
b0000000011010011 &
b0000000011010011 ,
1-
#2110000
0-
#2115000
b0000000011010100 &
b0000000011010100 ,
1-
#2120000
0-
#2125000
b0000000011010101 &
b0000000011010101 ,
1-
#2130000
0-
#2135000
b0000000011010110 &
b0000000011010110 ,
1-
#2140000
0-
#2145000
b0000000011010111 &
b0000000011010111 ,
1-
#2150000
0-
#2155000
b0000000011011000 &
b0000000011011000 ,
1-
#2160000
0-
#2165000
b0000000011011001 &
b0000000011011001 ,
1-
#2170000
0-
#2175000
b0000000011011010 &
b0000000011011010 ,
1-
#2180000
0-
#2185000
b0000000011011011 &
b0000000011011011 ,
1-
#2190000
0-
#2195000
b0000000011011100 &
b0000000011011100 ,
1-
#2200000
0-
#2205000
b0000000011011101 &
b0000000011011101 ,
1-
#2210000
0-
#2215000
b0000000011011110 &
b0000000011011110 ,
1-
#2220000
0-
#2225000
b0000000011011111 &
b0000000011011111 ,
1-
#2230000
0-
#2235000
b0000000011100000 &
b0000000011100000 ,
1-
#2240000
0-
#2245000
b0000000011100001 &
b0000000011100001 ,
1-
#2250000
0-
#2255000
b0000000011100010 &
b0000000011100010 ,
1-
#2260000
0-
#2265000
b0000000011100011 &
b0000000011100011 ,
1-
#2270000
0-
#2275000
b0000000011100100 &
b0000000011100100 ,
1-
#2280000
0-
#2285000
b0000000011100101 &
b0000000011100101 ,
1-
#2290000
0-
#2295000
b0000000011100110 &
b0000000011100110 ,
1-
#2300000
0-
#2305000
b0000000011100111 &
b0000000011100111 ,
1-
#2310000
0-
#2315000
b0000000011101000 &
b0000000011101000 ,
1-
#2320000
0-
#2325000
b0000000011101001 &
b0000000011101001 ,
1-
#2330000
0-
#2335000
b0000000011101010 &
b0000000011101010 ,
1-
#2340000
0-
#2345000
b0000000011101011 &
b0000000011101011 ,
1-
#2350000
0-
#2355000
b0000000011101100 &
b0000000011101100 ,
1-
#2360000
0-
#2365000
b0000000011101101 &
b0000000011101101 ,
1-
#2370000
0-
#2375000
b0000000011101110 &
b0000000011101110 ,
1-
#2380000
0-
#2385000
b0000000011101111 &
b0000000011101111 ,
1-
#2390000
0-
#2395000
b0000000011110000 &
b0000000011110000 ,
1-
#2400000
0-
#2405000
b0000000011110001 &
b0000000011110001 ,
1-
#2410000
0-
#2415000
b0000000011110010 &
b0000000011110010 ,
1-
#2420000
0-
#2425000
b0000000011110011 &
b0000000011110011 ,
1-
#2430000
0-
#2435000
b0000000011110100 &
b0000000011110100 ,
1-
#2440000
0-
#2445000
b0000000011110101 &
b0000000011110101 ,
1-
#2450000
0-
#2455000
b0000000011110110 &
b0000000011110110 ,
1-
#2460000
0-
#2465000
b0000000011110111 &
b0000000011110111 ,
1-
#2470000
0-
#2475000
b0000000011111000 &
b0000000011111000 ,
1-
#2480000
0-
#2485000
b0000000011111001 &
b0000000011111001 ,
1-
#2490000
0-
#2495000
b0000000011111010 &
b0000000011111010 ,
1-
#2500000
0-
#2505000
b0000000011111011 &
b0000000011111011 ,
1-
#2510000
0-
#2515000
b0000000011111100 &
b0000000011111100 ,
1-
#2520000
0-
#2525000
b0000000011111101 &
b0000000011111101 ,
1-
#2530000
0-
#2535000
b0000000011111110 &
b0000000011111110 ,
1-
#2540000
0-
#2545000
b0000000011111111 &
b0000000011111111 ,
1-
#2550000
0-
#2555000
b0000000100000000 &
b0000000100000000 ,
1-
#2560000
0-
#2565000
b0000000100000001 &
b0000000100000001 ,
1-
#2570000
0-
#2575000
b0000000100000010 &
b0000000100000010 ,
1-
#2580000
0-
#2585000
b0000000100000011 &
b0000000100000011 ,
1-
#2590000
0-
#2595000
b0000000100000100 &
b0000000100000100 ,
1-
#2600000
0-
#2605000
b0000000100000101 &
b0000000100000101 ,
1-
#2610000
0-
#2615000
b0000000100000110 &
b0000000100000110 ,
1-
#2620000
0-
#2625000
b0000000100000111 &
b0000000100000111 ,
1-
#2630000
0-
#2635000
b0000000100001000 &
b0000000100001000 ,
1-
#2640000
0-
#2645000
b0000000100001001 &
b0000000100001001 ,
1-
#2650000
0-
#2655000
b0000000100001010 &
b0000000100001010 ,
1-
#2660000
0-
#2665000
b0000000100001011 &
b0000000100001011 ,
1-
#2670000
0-
#2675000
b0000000100001100 &
b0000000100001100 ,
1-
#2680000
0-
#2685000
b0000000100001101 &
b0000000100001101 ,
1-
#2690000
0-
#2695000
b0000000100001110 &
b0000000100001110 ,
1-
#2700000
0-
#2705000
b0000000100001111 &
b0000000100001111 ,
1-
#2710000
0-
#2715000
b0000000100010000 &
b0000000100010000 ,
1-
#2720000
0-
#2725000
b0000000100010001 &
b0000000100010001 ,
1-
#2730000
0-
#2735000
b0000000100010010 &
b0000000100010010 ,
1-
#2740000
0-
#2745000
b0000000100010011 &
b0000000100010011 ,
1-
#2750000
0-
#2755000
b0000000100010100 &
b0000000100010100 ,
1-
#2760000
0-
#2765000
b0000000100010101 &
b0000000100010101 ,
1-
#2770000
0-
#2775000
b0000000100010110 &
b0000000100010110 ,
1-
#2780000
0-
#2785000
b0000000100010111 &
b0000000100010111 ,
1-
#2790000
0-
#2795000
b0000000100011000 &
b0000000100011000 ,
1-
#2800000
0-
#2805000
b0000000100011001 &
b0000000100011001 ,
1-
#2810000
0-
#2815000
b0000000100011010 &
b0000000100011010 ,
1-
#2820000
0-
#2825000
b0000000100011011 &
b0000000100011011 ,
1-
#2830000
0-
#2835000
b0000000100011100 &
b0000000100011100 ,
1-
#2840000
0-
#2845000
b0000000100011101 &
b0000000100011101 ,
1-
#2850000
0-
#2855000
b0000000100011110 &
b0000000100011110 ,
1-
#2860000
0-
#2865000
b0000000100011111 &
b0000000100011111 ,
1-
#2870000
0-
#2875000
b0000000100100000 &
b0000000100100000 ,
1-
#2880000
0-
#2885000
b0000000100100001 &
b0000000100100001 ,
1-
#2890000
0-
#2895000
b0000000100100010 &
b0000000100100010 ,
1-
#2900000
0-
#2905000
b0000000100100011 &
b0000000100100011 ,
1-
#2910000
0-
#2915000
b0000000100100100 &
b0000000100100100 ,
1-
#2920000
0-
#2925000
b0000000100100101 &
b0000000100100101 ,
1-
#2930000
0-
#2935000
b0000000100100110 &
b0000000100100110 ,
1-
#2940000
0-
#2945000
b0000000100100111 &
b0000000100100111 ,
1-
#2950000
0-
#2955000
b0000000100101000 &
b0000000100101000 ,
1-
#2960000
0-
#2965000
b0000000100101001 &
b0000000100101001 ,
1-
#2970000
0-
#2975000
b0000000100101010 &
b0000000100101010 ,
1-
#2980000
0-
#2985000
b0000000100101011 &
b0000000100101011 ,
1-
#2990000
0-
#2995000
b0000000100101100 &
b0000000100101100 ,
1-
#3000000
0-
#3005000
b0000000100101101 &
b0000000100101101 ,
1-
#3010000
0-
#3015000
b0000000100101110 &
b0000000100101110 ,
1-
#3020000
0-
#3025000
b0000000100101111 &
b0000000100101111 ,
1-
#3030000
0-
#3035000
b0000000100110000 &
b0000000100110000 ,
1-
#3040000
0-
#3045000
b0000000100110001 &
b0000000100110001 ,
1-
#3050000
0-
#3055000
b0000000100110010 &
b0000000100110010 ,
1-
#3060000
0-
#3065000
b0000000100110011 &
b0000000100110011 ,
1-
#3070000
0-
#3075000
b0000000100110100 &
b0000000100110100 ,
1-
#3080000
0-
#3085000
b0000000100110101 &
b0000000100110101 ,
1-
#3090000
0-
#3095000
b0000000100110110 &
b0000000100110110 ,
1-
#3100000
0-
#3105000
b0000000100110111 &
b0000000100110111 ,
1-
#3110000
0-
#3115000
b0000000100111000 &
b0000000100111000 ,
1-
#3120000
0-
#3125000
b0000000100111001 &
b0000000100111001 ,
1-
#3130000
0-
#3135000
b0000000100111010 &
b0000000100111010 ,
1-
#3140000
0-
#3145000
b0000000100111011 &
b0000000100111011 ,
1-
#3150000
0-
#3155000
b0000000100111100 &
b0000000100111100 ,
1-
#3160000
0-
#3165000
b0000000100111101 &
b0000000100111101 ,
1-
#3170000
0-
#3175000
b0000000100111110 &
b0000000100111110 ,
1-
#3180000
0-
#3185000
b0000000100111111 &
b0000000100111111 ,
1-
#3190000
0-
#3195000
b0000000101000000 &
b0000000101000000 ,
1-
#3200000
0-
#3205000
b0000000101000001 &
b0000000101000001 ,
1-
#3210000
0-
#3215000
b0000000101000010 &
b0000000101000010 ,
1-
#3220000
0-
#3225000
b0000000101000011 &
b0000000101000011 ,
1-
#3230000
0-
#3235000
b0000000101000100 &
b0000000101000100 ,
1-
#3240000
0-
#3245000
b0000000101000101 &
b0000000101000101 ,
1-
#3250000
0-
#3255000
b0000000101000110 &
b0000000101000110 ,
1-
#3260000
0-
#3265000
b0000000101000111 &
b0000000101000111 ,
1-
#3270000
0-
#3275000
b0000000101001000 &
b0000000101001000 ,
1-
#3280000
0-
#3285000
b0000000101001001 &
b0000000101001001 ,
1-
#3290000
0-
#3295000
b0000000101001010 &
b0000000101001010 ,
1-
#3300000
0-
#3305000
b0000000101001011 &
b0000000101001011 ,
1-
#3310000
0-
